___future___/__init__.py
print_function-1.0.2.dist-info/LICENSE
print_function-1.0.2.dist-info/METADATA
print_function-1.0.2.dist-info/WHEEL
print_function-1.0.2.dist-info/top_level.txt
print_function-1.0.2.dist-info/RECORD
