Metadata-Version: 2.1
Name: print-function
Version: 1.0.2
Summary: Best python print function
Home-page: https://github.com/raywu60kg/print-function
Author: raywu60kg
Author-email: wuhaohsiang1992@gmail.com
License: MIT
Platform: UNKNOWN
Classifier: Programming Language :: Python :: 3.4
Classifier: Programming Language :: Python :: 3.5
Classifier: Programming Language :: Python :: 3.6
Classifier: Programming Language :: Python :: 3.7
Classifier: Programming Language :: Python :: 3.8
Requires-Python: >=3.4
